E_C_2_RAUN_2/pshare/probador.v
module probador(
		input [32-1:0]nex_PC,
		input prediction,
		output reg reset,
		output reg clock,
		output reg [32-1:0]PC,
		output reg [32-1:0] etiqueta,
		output reg fix_result
	);
	
	initial begin
		$dumpfile("Mux.vcd");
		$dumpvars;
		$display ("\t\t\tclock,\treset,\tPC,\tnex_PC");
		$monitor($time,"\t%b\t%b\t\t%b\t%b", clock, reset,PC,nex_PC);
		
		// Valores iniciales de las señales.
		reset = 1;
		PC = 'h00000000;
		etiqueta = 'h00000000;        
		fix_result = 0;
		
		repeat (100) begin PC=0;
		repeat (10) begin				
        		@(posedge clock);
        			
        		reset = 0;
			PC = PC+1;
			etiqueta = etiqueta+10; 
			
			fix_result = 'b1;
		end end
		
		repeat (100) begin PC=0;
		repeat (10) begin				
        		@(posedge clock);
        			
        		reset = 0;
			PC = PC+1;
			etiqueta = etiqueta+10;   
			
			fix_result = 'b0;
		end end
		
		$finish;
		
	end
	// Reloj
	initial	clock 	<= 0;			// Valor inicial al reloj, sino siempre será indeterminado
	always	#1 clock 	<= ~clock;		// Hace "toggle" cada 4 segundos
endmodule

E_C_2_RAUN_2/pshare/tournament.v
module tournament #(parameter n=32, size=16)( //El alto de la tabla es (2**size)-1
			input reset,
			input clock,
			input fix_result,
			input [n-1:0]etiqueta,
			input [n-1:0]PC,
			output reg [n-1:0]nex_PC,
			output reg prediction);

reg [1:0]table_states[0:1000];
integer i;
reg [1:0]swich;
reg [n-1:0]miss;
reg [n-1:0]hit;

//Logica combinacional
always @(*) begin

	if (reset) begin
		swich[1:0] = 2'b00;
		miss[n-1:0] = 32'h00000000;
		hit[n-1:0] = 32'h00000000;
		
		for (i=0; i<=(2^size)-1; i++)
			table_states [i] = 2'b00;
	end
	else begin
		swich = table_states[PC];
		if ( swich == 2'b00 || swich == 2'b01)begin 
			nex_PC = PC+32'h00000004;
			prediction = 1'b0;
		end
		else begin
			nex_PC = PC+etiqueta;
			prediction = 1'b1;
		end	
	

		//Actualizar el BHT, planteamos varios casos, esto se hace instantaneo, el despase de tiempo lodebe de traer fix_result
		if (fix_result == 1 && prediction==0)//Fallamos!
			table_states[PC] = table_states[PC]+1'b1; //Nos acercamos a gshare
		else if (fix_result == 1 && prediction == 1) begin
			if (swich==2'b10)
				table_states[PC] = table_states[PC]+1'b1;
			else
				table_states[PC] = table_states[PC];
		end
		else if (fix_result == 0 && prediction == 0) begin
			if (swich==2'b01)
				table_states[PC] = table_states[PC]-1'b1; 
			else
				table_states[PC] = table_states[PC];
		end
		else
			table_states[PC] = table_states[PC]-1'b1;
			
		if (fix_result == prediction)
			hit = hit+1'b1;
		else
			miss = miss+1'b1;
	end 
end

endmodule

E_C_2_RAUN_2/pshare/Banco_de_Pruebas.v
`timescale 	1s				/ 100ps
// escala	unidad temporal (valor de "#4") / precisión
// Pueden omitirse y llamarse desde el testbench


`include "tournament.v"
`include "probador.v"
//`include "cmos_cells.v"



module BancoPruebas; // Testbench
	//Los buses se deben declarar en lineas aparte por ser de diferentes tamaños.
	wire reset;
	wire clock;
	wire [n-1:0]PC;
	wire [n-1:0] etiqueta;
	wire [n-1:0]nex_PC;
	wire prediction;
	
	parameter n=32;
	parameter size=16;

	// Descripción conductual de alarma, las instancias se realizan por medio de AUTOINST.
	tournament #(/*AUTOINSTPARAM*/
		     // Parameters
		     .n			(n),
		     .size		(size)) tournament_inst ( /*AUTOINST*/
								 // Outputs
								 .nex_PC		(nex_PC[n-1:0]),
								 .prediction		(prediction),
								 // Inputs
								 .reset			(reset),
								 .clock			(clock),
								 .fix_result		(fix_result),
								 .etiqueta		(etiqueta[n-1:0]),
								 .PC			(PC[n-1:0]));
						
	
	
	// Probador: generador de señales y monitor
	probador probador_Inst( /*AUTOINST*/
			       // Outputs
			       .reset		(reset),
			       .clock		(clock),
			       .PC		(PC[32-1:0]),
			       .etiqueta	(etiqueta[32-1:0]),
			       .fix_result	(fix_result),
			       // Inputs
			       .nex_PC		(nex_PC[32-1:0]),
			       .prediction	(prediction));
endmodule

E_C_2_RAUN_2/pshare/Mux.vcd
$date
	Wed May 19 15:07:10 2021
$end
$version
	Icarus Verilog
$end
$timescale
	100ps
$end
$scope module BancoPruebas $end
$var wire 1 ! reset $end
$var wire 1 " prediction $end
$var wire 32 # nex_PC [31:0] $end
$var wire 1 $ fix_result $end
$var wire 32 % etiqueta [31:0] $end
$var wire 1 & clock $end
$var wire 32 ' PC [31:0] $end
$scope module probador_Inst $end
$var wire 1 " prediction $end
$var wire 32 ( nex_PC [31:0] $end
$var reg 32 ) PC [31:0] $end
$var reg 1 & clock $end
$var reg 32 * etiqueta [31:0] $end
$var reg 1 $ fix_result $end
$var reg 1 ! reset $end
$upscope $end
$scope module tournament_inst $end
$var wire 32 + PC [31:0] $end
$var wire 1 & clock $end
$var wire 32 , etiqueta [31:0] $end
$var wire 1 $ fix_result $end
$var wire 1 ! reset $end
$var reg 32 - hit [31:0] $end
$var reg 32 . miss [31:0] $end
$var reg 32 / nex_PC [31:0] $end
$var reg 1 " prediction $end
$var reg 2 0 swich [1:0] $end
$var integer 32 1 i [31:0] $end
$upscope $end
$upscope $end
$enddefinitions $end
#0
$dumpvars
b10010 1
b0 0
bx /
b0 .
b0 -
b0 ,
b0 +
b0 *
b0 )
bx (
b0 '
0&
b0 %
0$
bx #
x"
1!
$end
#10000000000
b1 .
0"
b101 #
b101 (
b101 /
1$
b1010 %
b1010 *
b1010 ,
b1 '
b1 )
b1 +
0!
1&
#20000000000
0&
#30000000000
b10 .
b110 #
b110 (
b110 /
b10100 %
b10100 *
b10100 ,
b10 '
b10 )
b10 +
1&
#40000000000
0&
#50000000000
b11 .
b111 #
b111 (
b111 /
b11110 %
b11110 *
b11110 ,
b11 '
b11 )
b11 +
1&
#60000000000
0&
#70000000000
b100 .
b1000 #
b1000 (
b1000 /
b101000 %
b101000 *
b101000 ,
b100 '
b100 )
b100 +
1&
#80000000000
0&
#90000000000
b101 .
b1001 #
b1001 (
b1001 /
b110010 %
b110010 *
b110010 ,
b101 '
b101 )
b101 +
1&
#100000000000
0&
#110000000000
b110 .
b1010 #
b1010 (
b1010 /
b111100 %
b111100 *
b111100 ,
b110 '
b110 )
b110 +
1&
#120000000000
0&
#130000000000
b111 .
b1011 #
b1011 (
b1011 /
b1000110 %
b1000110 *
b1000110 ,
b111 '
b111 )
b111 +
1&
#140000000000
0&
#150000000000
b1000 .
b1100 #
b1100 (
b1100 /
b1010000 %
b1010000 *
b1010000 ,
b1000 '
b1000 )
b1000 +
1&
#160000000000
0&
#170000000000
b1001 .
b1101 #
b1101 (
b1101 /
b1011010 %
b1011010 *
b1011010 ,
b1001 '
b1001 )
b1001 +
1&
#180000000000
0&
#190000000000
b1010 .
b100 #
b100 (
b100 /
b1100100 %
b1100100 *
b1100100 ,
b0 '
b0 )
b0 +
1&
#200000000000
0&
#210000000000
b1011 .
b101 #
b101 (
b101 /
b1 0
b1101110 %
b1101110 *
b1101110 ,
b1 '
b1 )
b1 +
1&
#220000000000
0&
#230000000000
b1100 .
b110 #
b110 (
b110 /
b1111000 %
b1111000 *
b1111000 ,
b10 '
b10 )
b10 +
1&
#240000000000
0&
#250000000000
b1101 .
b111 #
b111 (
b111 /
b10000010 %
b10000010 *
b10000010 ,
b11 '
b11 )
b11 +
1&
#260000000000
0&
#270000000000
b1110 .
b1000 #
b1000 (
b1000 /
b10001100 %
b10001100 *
b10001100 ,
b100 '
b100 )
b100 +
1&
#280000000000
0&
#290000000000
b1111 .
b1001 #
b1001 (
b1001 /
b10010110 %
b10010110 *
b10010110 ,
b101 '
b101 )
b101 +
1&
#300000000000
0&
#310000000000
b10000 .
b1010 #
b1010 (
b1010 /
b10100000 %
b10100000 *
b10100000 ,
b110 '
b110 )
b110 +
1&
#320000000000
0&
#330000000000
b10001 .
b1011 #
b1011 (
b1011 /
b10101010 %
b10101010 *
b10101010 ,
b111 '
b111 )
b111 +
1&
#340000000000
0&
#350000000000
b10010 .
b1100 #
b1100 (
b1100 /
b10110100 %
b10110100 *
b10110100 ,
b1000 '
b1000 )
b1000 +
1&
#360000000000
0&
#370000000000
b10011 .
b1101 #
b1101 (
b1101 /
b10111110 %
b10111110 *
b10111110 ,
b1001 '
b1001 )
b1001 +
1&
#380000000000
0&
#390000000000
b10100 .
b100 #
b100 (
b100 /
b11001000 %
b11001000 *
b11001000 ,
b0 '
b0 )
b0 +
1&
#400000000000
0&
#410000000000
b1 -
1"
b11010011 #
b11010011 (
b11010011 /
b10 0
b11010010 %
b11010010 *
b11010010 ,
b1 '
b1 )
b1 +
1&
#420000000000
0&
#430000000000
b10 -
b11011110 #
b11011110 (
b11011110 /
b11011100 %
b11011100 *
b11011100 ,
b10 '
b10 )
b10 +
1&
#440000000000
0&
#450000000000
b11 -
b11101001 #
b11101001 (
b11101001 /
b11100110 %
b11100110 *
b11100110 ,
b11 '
b11 )
b11 +
1&
#460000000000
0&
#470000000000
b100 -
b11110100 #
b11110100 (
b11110100 /
b11110000 %
b11110000 *
b11110000 ,
b100 '
b100 )
b100 +
1&
#480000000000
0&
#490000000000
b101 -
b11111111 #
b11111111 (
b11111111 /
b11111010 %
b11111010 *
b11111010 ,
b101 '
b101 )
b101 +
1&
#500000000000
0&
#510000000000
b110 -
b100001010 #
b100001010 (
b100001010 /
b100000100 %
b100000100 *
b100000100 ,
b110 '
b110 )
b110 +
1&
#520000000000
0&
#530000000000
b111 -
b100010101 #
b100010101 (
b100010101 /
b100001110 %
b100001110 *
b100001110 ,
b111 '
b111 )
b111 +
1&
#540000000000
0&
#550000000000
b1000 -
b100100000 #
b100100000 (
b100100000 /
b100011000 %
b100011000 *
b100011000 ,
b1000 '
b1000 )
b1000 +
1&
#560000000000
0&
#570000000000
b1001 -
b100101011 #
b100101011 (
b100101011 /
b100100010 %
b100100010 *
b100100010 ,
b1001 '
b1001 )
b1001 +
1&
#580000000000
0&
#590000000000
b1010 -
b100101100 #
b100101100 (
b100101100 /
b100101100 %
b100101100 *
b100101100 ,
b0 '
b0 )
b0 +
1&
#600000000000
0&
#610000000000
b1011 -
b100110111 #
b100110111 (
b100110111 /
b11 0
b100110110 %
b100110110 *
b100110110 ,
b1 '
b1 )
b1 +
1&
#620000000000
0&
#630000000000
b1100 -
b101000010 #
b101000010 (
b101000010 /
b101000000 %
b101000000 *
b101000000 ,
b10 '
b10 )
b10 +
1&
#640000000000
0&
#650000000000
b1101 -
b101001101 #
b101001101 (
b101001101 /
b101001010 %
b101001010 *
b101001010 ,
b11 '
b11 )
b11 +
1&
#660000000000
0&
#670000000000
b1110 -
b101011000 #
b101011000 (
b101011000 /
b101010100 %
b101010100 *
b101010100 ,
b100 '
b100 )
b100 +
1&
#680000000000
0&
#690000000000
b1111 -
b101100011 #
b101100011 (
b101100011 /
b101011110 %
b101011110 *
b101011110 ,
b101 '
b101 )
b101 +
1&
#700000000000
0&
#710000000000
b10000 -
b101101110 #
b101101110 (
b101101110 /
b101101000 %
b101101000 *
b101101000 ,
b110 '
b110 )
b110 +
1&
#720000000000
0&
#730000000000
b10001 -
b101111001 #
b101111001 (
b101111001 /
b101110010 %
b101110010 *
b101110010 ,
b111 '
b111 )
b111 +
1&
#740000000000
0&
#750000000000
b10010 -
b110000100 #
b110000100 (
b110000100 /
b101111100 %
b101111100 *
b101111100 ,
b1000 '
b1000 )
b1000 +
1&
#760000000000
0&
#770000000000
b10011 -
b110001111 #
b110001111 (
b110001111 /
b110000110 %
b110000110 *
b110000110 ,
b1001 '
b1001 )
b1001 +
1&
#780000000000
0&
#790000000000
b10100 -
b110010000 #
b110010000 (
b110010000 /
b110010000 %
b110010000 *
b110010000 ,
b0 '
b0 )
b0 +
1&
#800000000000
0&
#810000000000
b10101 -
b110011011 #
b110011011 (
b110011011 /
b110011010 %
b110011010 *
b110011010 ,
b1 '
b1 )
b1 +
1&
#820000000000
0&
#830000000000
b10110 -
b110100110 #
b110100110 (
b110100110 /
b110100100 %
b110100100 *
b110100100 ,
b10 '
b10 )
b10 +
1&
#840000000000
0&
#850000000000
b10111 -
b110110001 #
b110110001 (
b110110001 /
b110101110 %
b110101110 *
b110101110 ,
b11 '
b11 )
b11 +
1&
#860000000000
0&
#870000000000
b11000 -
b110111100 #
b110111100 (
b110111100 /
b110111000 %
b110111000 *
b110111000 ,
b100 '
b100 )
b100 +
1&
#880000000000
0&
#890000000000
b11001 -
b111000111 #
b111000111 (
b111000111 /
b111000010 %
b111000010 *
b111000010 ,
b101 '
b101 )
b101 +
1&
#900000000000
0&
#910000000000
b11010 -
b111010010 #
b111010010 (
b111010010 /
b111001100 %
b111001100 *
b111001100 ,
b110 '
b110 )
b110 +
1&
#920000000000
0&
#930000000000
b11011 -
b111011101 #
b111011101 (
b111011101 /
b111010110 %
b111010110 *
b111010110 ,
b111 '
b111 )
b111 +
1&
#940000000000
0&
#950000000000
b11100 -
b111101000 #
b111101000 (
b111101000 /
b111100000 %
b111100000 *
b111100000 ,
b1000 '
b1000 )
b1000 +
1&
#960000000000
0&
#970000000000
b11101 -
b111110011 #
b111110011 (
b111110011 /
b111101010 %
b111101010 *
b111101010 ,
b1001 '
b1001 )
b1001 +
1&
#980000000000
0&
#990000000000
b11110 -
b111110100 #
b111110100 (
b111110100 /
b111110100 %
b111110100 *
b111110100 ,
b0 '
b0 )
b0 +
1&
#1000000000000
0&
#1010000000000
b11111 -
b111111111 #
b111111111 (
b111111111 /
b111111110 %
b111111110 *
b111111110 ,
b1 '
b1 )
b1 +
1&
#1020000000000
0&
#1030000000000
b100000 -
b1000001010 #
b1000001010 (
b1000001010 /
b1000001000 %
b1000001000 *
b1000001000 ,
b10 '
b10 )
b10 +
1&
#1040000000000
0&
#1050000000000
b100001 -
b1000010101 #
b1000010101 (
b1000010101 /
b1000010010 %
b1000010010 *
b1000010010 ,
b11 '
b11 )
b11 +
1&
#1060000000000
0&
#1070000000000
b100010 -
b1000100000 #
b1000100000 (
b1000100000 /
b1000011100 %
b1000011100 *
b1000011100 ,
b100 '
b100 )
b100 +
1&
#1080000000000
0&
#1090000000000
b100011 -
b1000101011 #
b1000101011 (
b1000101011 /
b1000100110 %
b1000100110 *
b1000100110 ,
b101 '
b101 )
b101 +
1&
#1100000000000
0&
#1110000000000
b100100 -
b1000110110 #
b1000110110 (
b1000110110 /
b1000110000 %
b1000110000 *
b1000110000 ,
b110 '
b110 )
b110 +
1&
#1120000000000
0&
#1130000000000
b100101 -
b1001000001 #
b1001000001 (
b1001000001 /
b1000111010 %
b1000111010 *
b1000111010 ,
b111 '
b111 )
b111 +
1&
#1140000000000
0&
#1150000000000
b100110 -
b1001001100 #
b1001001100 (
b1001001100 /
b1001000100 %
b1001000100 *
b1001000100 ,
b1000 '
b1000 )
b1000 +
1&
#1160000000000
0&
#1170000000000
b100111 -
b1001010111 #
b1001010111 (
b1001010111 /
b1001001110 %
b1001001110 *
b1001001110 ,
b1001 '
b1001 )
b1001 +
1&
#1180000000000
0&
#1190000000000
b101000 -
b1001011000 #
b1001011000 (
b1001011000 /
b1001011000 %
b1001011000 *
b1001011000 ,
b0 '
b0 )
b0 +
1&
#1200000000000
0&
#1210000000000
b101001 -
b1001100011 #
b1001100011 (
b1001100011 /
b1001100010 %
b1001100010 *
b1001100010 ,
b1 '
b1 )
b1 +
1&
#1220000000000
0&
#1230000000000
b101010 -
b1001101110 #
b1001101110 (
b1001101110 /
b1001101100 %
b1001101100 *
b1001101100 ,
b10 '
b10 )
b10 +
1&
#1240000000000
0&
#1250000000000
b101011 -
b1001111001 #
b1001111001 (
b1001111001 /
b1001110110 %
b1001110110 *
b1001110110 ,
b11 '
b11 )
b11 +
1&
#1260000000000
0&
#1270000000000
b101100 -
b1010000100 #
b1010000100 (
b1010000100 /
b1010000000 %
b1010000000 *
b1010000000 ,
b100 '
b100 )
b100 +
1&
#1280000000000
0&
#1290000000000
b101101 -
b1010001111 #
b1010001111 (
b1010001111 /
b1010001010 %
b1010001010 *
b1010001010 ,
b101 '
b101 )
b101 +
1&
#1300000000000
0&
#1310000000000
b101110 -
b1010011010 #
b1010011010 (
b1010011010 /
b1010010100 %
b1010010100 *
b1010010100 ,
b110 '
b110 )
b110 +
1&
#1320000000000
0&
#1330000000000
b101111 -
b1010100101 #
b1010100101 (
b1010100101 /
b1010011110 %
b1010011110 *
b1010011110 ,
b111 '
b111 )
b111 +
1&
#1340000000000
0&
#1350000000000
b110000 -
b1010110000 #
b1010110000 (
b1010110000 /
b1010101000 %
b1010101000 *
b1010101000 ,
b1000 '
b1000 )
b1000 +
1&
#1360000000000
0&
#1370000000000
b110001 -
b1010111011 #
b1010111011 (
b1010111011 /
b1010110010 %
b1010110010 *
b1010110010 ,
b1001 '
b1001 )
b1001 +
1&
#1380000000000
0&
#1390000000000
b110010 -
b1010111100 #
b1010111100 (
b1010111100 /
b1010111100 %
b1010111100 *
b1010111100 ,
b0 '
b0 )
b0 +
1&
#1400000000000
0&
#1410000000000
b110011 -
b1011000111 #
b1011000111 (
b1011000111 /
b1011000110 %
b1011000110 *
b1011000110 ,
b1 '
b1 )
b1 +
1&
#1420000000000
0&
#1430000000000
b110100 -
b1011010010 #
b1011010010 (
b1011010010 /
b1011010000 %
b1011010000 *
b1011010000 ,
b10 '
b10 )
b10 +
1&
#1440000000000
0&
#1450000000000
b110101 -
b1011011101 #
b1011011101 (
b1011011101 /
b1011011010 %
b1011011010 *
b1011011010 ,
b11 '
b11 )
b11 +
1&
#1460000000000
0&
#1470000000000
b110110 -
b1011101000 #
b1011101000 (
b1011101000 /
b1011100100 %
b1011100100 *
b1011100100 ,
b100 '
b100 )
b100 +
1&
#1480000000000
0&
#1490000000000
b110111 -
b1011110011 #
b1011110011 (
b1011110011 /
b1011101110 %
b1011101110 *
b1011101110 ,
b101 '
b101 )
b101 +
1&
#1500000000000
0&
#1510000000000
b111000 -
b1011111110 #
b1011111110 (
b1011111110 /
b1011111000 %
b1011111000 *
b1011111000 ,
b110 '
b110 )
b110 +
1&
#1520000000000
0&
#1530000000000
b111001 -
b1100001001 #
b1100001001 (
b1100001001 /
b1100000010 %
b1100000010 *
b1100000010 ,
b111 '
b111 )
b111 +
1&
#1540000000000
0&
#1550000000000
b111010 -
b1100010100 #
b1100010100 (
b1100010100 /
b1100001100 %
b1100001100 *
b1100001100 ,
b1000 '
b1000 )
b1000 +
1&
#1560000000000
0&
#1570000000000
b111011 -
b1100011111 #
b1100011111 (
b1100011111 /
b1100010110 %
b1100010110 *
b1100010110 ,
b1001 '
b1001 )
b1001 +
1&
#1580000000000
0&
#1590000000000
b111100 -
b1100100000 #
b1100100000 (
b1100100000 /
b1100100000 %
b1100100000 *
b1100100000 ,
b0 '
b0 )
b0 +
1&
#1600000000000
0&
#1610000000000
b111101 -
b1100101011 #
b1100101011 (
b1100101011 /
b1100101010 %
b1100101010 *
b1100101010 ,
b1 '
b1 )
b1 +
1&
#1620000000000
0&
#1630000000000
b111110 -
b1100110110 #
b1100110110 (
b1100110110 /
b1100110100 %
b1100110100 *
b1100110100 ,
b10 '
b10 )
b10 +
1&
#1640000000000
0&
#1650000000000
b111111 -
b1101000001 #
b1101000001 (
b1101000001 /
b1100111110 %
b1100111110 *
b1100111110 ,
b11 '
b11 )
b11 +
1&
#1660000000000
0&
#1670000000000
b1000000 -
b1101001100 #
b1101001100 (
b1101001100 /
b1101001000 %
b1101001000 *
b1101001000 ,
b100 '
b100 )
b100 +
1&
#1680000000000
0&
#1690000000000
b1000001 -
b1101010111 #
b1101010111 (
b1101010111 /
b1101010010 %
b1101010010 *
b1101010010 ,
b101 '
b101 )
b101 +
1&
#1700000000000
0&
#1710000000000
b1000010 -
b1101100010 #
b1101100010 (
b1101100010 /
b1101011100 %
b1101011100 *
b1101011100 ,
b110 '
b110 )
b110 +
1&
#1720000000000
0&
#1730000000000
b1000011 -
b1101101101 #
b1101101101 (
b1101101101 /
b1101100110 %
b1101100110 *
b1101100110 ,
b111 '
b111 )
b111 +
1&
#1740000000000
0&
#1750000000000
b1000100 -
b1101111000 #
b1101111000 (
b1101111000 /
b1101110000 %
b1101110000 *
b1101110000 ,
b1000 '
b1000 )
b1000 +
1&
#1760000000000
0&
#1770000000000
b1000101 -
b1110000011 #
b1110000011 (
b1110000011 /
b1101111010 %
b1101111010 *
b1101111010 ,
b1001 '
b1001 )
b1001 +
1&
#1780000000000
0&
#1790000000000
b1000110 -
b1110000100 #
b1110000100 (
b1110000100 /
b1110000100 %
b1110000100 *
b1110000100 ,
b0 '
b0 )
b0 +
1&
#1800000000000
0&
#1810000000000
b1000111 -
b1110001111 #
b1110001111 (
b1110001111 /
b1110001110 %
b1110001110 *
b1110001110 ,
b1 '
b1 )
b1 +
1&
#1820000000000
0&
#1830000000000
b1001000 -
b1110011010 #
b1110011010 (
b1110011010 /
b1110011000 %
b1110011000 *
b1110011000 ,
b10 '
b10 )
b10 +
1&
#1840000000000
0&
#1850000000000
b1001001 -
b1110100101 #
b1110100101 (
b1110100101 /
b1110100010 %
b1110100010 *
b1110100010 ,
b11 '
b11 )
b11 +
1&
#1860000000000
0&
#1870000000000
b1001010 -
b1110110000 #
b1110110000 (
b1110110000 /
b1110101100 %
b1110101100 *
b1110101100 ,
b100 '
b100 )
b100 +
1&
#1880000000000
0&
#1890000000000
b1001011 -
b1110111011 #
b1110111011 (
b1110111011 /
b1110110110 %
b1110110110 *
b1110110110 ,
b101 '
b101 )
b101 +
1&
#1900000000000
0&
#1910000000000
b1001100 -
b1111000110 #
b1111000110 (
b1111000110 /
b1111000000 %
b1111000000 *
b1111000000 ,
b110 '
b110 )
b110 +
1&
#1920000000000
0&
#1930000000000
b1001101 -
b1111010001 #
b1111010001 (
b1111010001 /
b1111001010 %
b1111001010 *
b1111001010 ,
b111 '
b111 )
b111 +
1&
#1940000000000
0&
#1950000000000
b1001110 -
b1111011100 #
b1111011100 (
b1111011100 /
b1111010100 %
b1111010100 *
b1111010100 ,
b1000 '
b1000 )
b1000 +
1&
#1960000000000
0&
#1970000000000
b1001111 -
b1111100111 #
b1111100111 (
b1111100111 /
b1111011110 %
b1111011110 *
b1111011110 ,
b1001 '
b1001 )
b1001 +
1&
#1980000000000
0&
#1990000000000
b1010000 -
b1111101000 #
b1111101000 (
b1111101000 /
b1111101000 %
b1111101000 *
b1111101000 ,
b0 '
b0 )
b0 +
1&
#2000000000000
0&
#2010000000000
b1010001 -
b1111110011 #
b1111110011 (
b1111110011 /
b1111110010 %
b1111110010 *
b1111110010 ,
b1 '
b1 )
b1 +
1&
#2020000000000
0&
#2030000000000
b1010010 -
b1111111110 #
b1111111110 (
b1111111110 /
b1111111100 %
b1111111100 *
b1111111100 ,
b10 '
b10 )
b10 +
1&
#2040000000000
0&
#2050000000000
b1010011 -
b10000001001 #
b10000001001 (
b10000001001 /
b10000000110 %
b10000000110 *
b10000000110 ,
b11 '
b11 )
b11 +
1&
#2060000000000
0&
#2070000000000
b1010100 -
b10000010100 #
b10000010100 (
b10000010100 /
b10000010000 %
b10000010000 *
b10000010000 ,
b100 '
b100 )
b100 +
1&
#2080000000000
0&
#2090000000000
b1010101 -
b10000011111 #
b10000011111 (
b10000011111 /
b10000011010 %
b10000011010 *
b10000011010 ,
b101 '
b101 )
b101 +
1&
#2100000000000
0&
#2110000000000
b1010110 -
b10000101010 #
b10000101010 (
b10000101010 /
b10000100100 %
b10000100100 *
b10000100100 ,
b110 '
b110 )
b110 +
1&
#2120000000000
0&
#2130000000000
b1010111 -
b10000110101 #
b10000110101 (
b10000110101 /
b10000101110 %
b10000101110 *
b10000101110 ,
b111 '
b111 )
b111 +
1&
#2140000000000
0&
#2150000000000
b1011000 -
b10001000000 #
b10001000000 (
b10001000000 /
b10000111000 %
b10000111000 *
b10000111000 ,
b1000 '
b1000 )
b1000 +
1&
#2160000000000
0&
#2170000000000
b1011001 -
b10001001011 #
b10001001011 (
b10001001011 /
b10001000010 %
b10001000010 *
b10001000010 ,
b1001 '
b1001 )
b1001 +
1&
#2180000000000
0&
#2190000000000
b1011010 -
b10001001100 #
b10001001100 (
b10001001100 /
b10001001100 %
b10001001100 *
b10001001100 ,
b0 '
b0 )
b0 +
1&
#2200000000000
0&
#2210000000000
b1011011 -
b10001010111 #
b10001010111 (
b10001010111 /
b10001010110 %
b10001010110 *
b10001010110 ,
b1 '
b1 )
b1 +
1&
#2220000000000
0&
#2230000000000
b1011100 -
b10001100010 #
b10001100010 (
b10001100010 /
b10001100000 %
b10001100000 *
b10001100000 ,
b10 '
b10 )
b10 +
1&
#2240000000000
0&
#2250000000000
b1011101 -
b10001101101 #
b10001101101 (
b10001101101 /
b10001101010 %
b10001101010 *
b10001101010 ,
b11 '
b11 )
b11 +
1&
#2260000000000
0&
#2270000000000
b1011110 -
b10001111000 #
b10001111000 (
b10001111000 /
b10001110100 %
b10001110100 *
b10001110100 ,
b100 '
b100 )
b100 +
1&
#2280000000000
0&
#2290000000000
b1011111 -
b10010000011 #
b10010000011 (
b10010000011 /
b10001111110 %
b10001111110 *
b10001111110 ,
b101 '
b101 )
b101 +
1&
#2300000000000
0&
#2310000000000
b1100000 -
b10010001110 #
b10010001110 (
b10010001110 /
b10010001000 %
b10010001000 *
b10010001000 ,
b110 '
b110 )
b110 +
1&
#2320000000000
0&
#2330000000000
b1100001 -
b10010011001 #
b10010011001 (
b10010011001 /
b10010010010 %
b10010010010 *
b10010010010 ,
b111 '
b111 )
b111 +
1&
#2340000000000
0&
#2350000000000
b1100010 -
b10010100100 #
b10010100100 (
b10010100100 /
b10010011100 %
b10010011100 *
b10010011100 ,
b1000 '
b1000 )
b1000 +
1&
#2360000000000
0&
#2370000000000
b1100011 -
b10010101111 #
b10010101111 (
b10010101111 /
b10010100110 %
b10010100110 *
b10010100110 ,
b1001 '
b1001 )
b1001 +
1&
#2380000000000
0&
#2390000000000
b1100100 -
b10010110000 #
b10010110000 (
b10010110000 /
b10010110000 %
b10010110000 *
b10010110000 ,
b0 '
b0 )
b0 +
1&
#2400000000000
0&
#2410000000000
b1100101 -
b10010111011 #
b10010111011 (
b10010111011 /
b10010111010 %
b10010111010 *
b10010111010 ,
b1 '
b1 )
b1 +
1&
#2420000000000
0&
#2430000000000
b1100110 -
b10011000110 #
b10011000110 (
b10011000110 /
b10011000100 %
b10011000100 *
b10011000100 ,
b10 '
b10 )
b10 +
1&
#2440000000000
0&
#2450000000000
b1100111 -
b10011010001 #
b10011010001 (
b10011010001 /
b10011001110 %
b10011001110 *
b10011001110 ,
b11 '
b11 )
b11 +
1&
#2460000000000
0&
#2470000000000
b1101000 -
b10011011100 #
b10011011100 (
b10011011100 /
b10011011000 %
b10011011000 *
b10011011000 ,
b100 '
b100 )
b100 +
1&
#2480000000000
0&
#2490000000000
b1101001 -
b10011100111 #
b10011100111 (
b10011100111 /
b10011100010 %
b10011100010 *
b10011100010 ,
b101 '
b101 )
b101 +
1&
#2500000000000
0&
#2510000000000
b1101010 -
b10011110010 #
b10011110010 (
b10011110010 /
b10011101100 %
b10011101100 *
b10011101100 ,
b110 '
b110 )
b110 +
1&
#2520000000000
0&
#2530000000000
b1101011 -
b10011111101 #
b10011111101 (
b10011111101 /
b10011110110 %
b10011110110 *
b10011110110 ,
b111 '
b111 )
b111 +
1&
#2540000000000
0&
#2550000000000
b1101100 -
b10100001000 #
b10100001000 (
b10100001000 /
b10100000000 %
b10100000000 *
b10100000000 ,
b1000 '
b1000 )
b1000 +
1&
#2560000000000
0&
#2570000000000
b1101101 -
b10100010011 #
b10100010011 (
b10100010011 /
b10100001010 %
b10100001010 *
b10100001010 ,
b1001 '
b1001 )
b1001 +
1&
#2580000000000
0&
#2590000000000
b1101110 -
b10100010100 #
b10100010100 (
b10100010100 /
b10100010100 %
b10100010100 *
b10100010100 ,
b0 '
b0 )
b0 +
1&
#2600000000000
0&
#2610000000000
b1101111 -
b10100011111 #
b10100011111 (
b10100011111 /
b10100011110 %
b10100011110 *
b10100011110 ,
b1 '
b1 )
b1 +
1&
#2620000000000
0&
#2630000000000
b1110000 -
b10100101010 #
b10100101010 (
b10100101010 /
b10100101000 %
b10100101000 *
b10100101000 ,
b10 '
b10 )
b10 +
1&
#2640000000000
0&
#2650000000000
b1110001 -
b10100110101 #
b10100110101 (
b10100110101 /
b10100110010 %
b10100110010 *
b10100110010 ,
b11 '
b11 )
b11 +
1&
#2660000000000
0&
#2670000000000
b1110010 -
b10101000000 #
b10101000000 (
b10101000000 /
b10100111100 %
b10100111100 *
b10100111100 ,
b100 '
b100 )
b100 +
1&
#2680000000000
0&
#2690000000000
b1110011 -
b10101001011 #
b10101001011 (
b10101001011 /
b10101000110 %
b10101000110 *
b10101000110 ,
b101 '
b101 )
b101 +
1&
#2700000000000
0&
#2710000000000
b1110100 -
b10101010110 #
b10101010110 (
b10101010110 /
b10101010000 %
b10101010000 *
b10101010000 ,
b110 '
b110 )
b110 +
1&
#2720000000000
0&
#2730000000000
b1110101 -
b10101100001 #
b10101100001 (
b10101100001 /
b10101011010 %
b10101011010 *
b10101011010 ,
b111 '
b111 )
b111 +
1&
#2740000000000
0&
#2750000000000
b1110110 -
b10101101100 #
b10101101100 (
b10101101100 /
b10101100100 %
b10101100100 *
b10101100100 ,
b1000 '
b1000 )
b1000 +
1&
#2760000000000
0&
#2770000000000
b1110111 -
b10101110111 #
b10101110111 (
b10101110111 /
b10101101110 %
b10101101110 *
b10101101110 ,
b1001 '
b1001 )
b1001 +
1&
#2780000000000
0&
#2790000000000
b1111000 -
b10101111000 #
b10101111000 (
b10101111000 /
b10101111000 %
b10101111000 *
b10101111000 ,
b0 '
b0 )
b0 +
1&
#2800000000000
0&
